dqrobotics_extensions/pyplot/__init__.py
dqrobotics_extensions/pyplot/_pyplot.py
dqrobotics_extensions/pyplot/example.py
dqrobotics_extensions/pyplot/example_animation.py
dqrobotics_extensions/pyplot/gallery/__init__.py
dqrobotics_extensions/pyplot/gallery/_output_lines.py
dqrobotics_extensions/pyplot/gallery/_output_moving_manipulators.py
dqrobotics_extensions/pyplot/gallery/_output_moving_primitives.py
dqrobotics_extensions/pyplot/gallery/_output_planes.py
dqrobotics_extensions/pyplot/gallery/_output_poses.py
dqrobotics_extensions/pyplot/gallery/_output_spheres.py
dqrobotics_extensions/pyplot/gallery/_utils.py
dqrobotics_extensions/pyplot/gallery/output_doc_samples.py
dqrobotics_pyplot-25.4.0.57.dist-info/licenses/LICENSE
dqrobotics_pyplot-25.4.0.57.dist-info/METADATA
dqrobotics_pyplot-25.4.0.57.dist-info/WHEEL
dqrobotics_pyplot-25.4.0.57.dist-info/entry_points.txt
dqrobotics_pyplot-25.4.0.57.dist-info/top_level.txt
dqrobotics_pyplot-25.4.0.57.dist-info/RECORD
